{
"type": "FeatureCollection",
"name": "gwanak_smartpoles",
"crs": { "type": "name", "properties": { "name": "urn:ogc:def:crs:OGC:1.3:CRS84" } },
"features": [
{ "type": "Feature", "properties": { "연번": 1, "스마트폴 유형": "CCTV 통합 스마트폴", "설치장소": "서울특별시 관악구 신림로 137", "위도": 37.47115475, "경도": 126.9340511, "보안등여부": "Y", "보행신호등여부": "N", "공공와이파이설치여부": "Y", "CCTV설치여부": "Y", "LED비상벨설치여부": "Y", "시각장애인용 음양신호기 여부": "N", "스피커탑재여부": "Y", "로고젝터 탑재여부": "N", "lat": 37.47115475, "lon": 126.9340511, "facility_group": "smartpole", "center_lon": 126.9340511, "center_lat": 37.47115475, "geometry_wkt": "POINT (126.934051 37.471155)", "source_dataset": "Gwanak Smartpole CSV" }, "geometry": { "type": "Point", "coordinates": [ 126.9340511, 37.47115475 ] } },
{ "type": "Feature", "properties": { "연번": 2, "스마트폴 유형": "CCTV 통합 스마트폴", "설치장소": "서울특별시 관악구 신림로 89", "위도": 37.47029068, "경도": 126.939524, "보안등여부": "Y", "보행신호등여부": "Y", "공공와이파이설치여부": "Y", "CCTV설치여부": "Y", "LED비상벨설치여부": "Y", "시각장애인용 음양신호기 여부": "Y", "스피커탑재여부": "Y", "로고젝터 탑재여부": "N", "lat": 37.47029068, "lon": 126.939524, "facility_group": "smartpole", "center_lon": 126.939524, "center_lat": 37.47029068, "geometry_wkt": "POINT (126.939524 37.470291)", "source_dataset": "Gwanak Smartpole CSV" }, "geometry": { "type": "Point", "coordinates": [ 126.939524, 37.47029068 ] } },
{ "type": "Feature", "properties": { "연번": 3, "스마트폴 유형": "CCTV 통합 스마트폴", "설치장소": "서울특별시 관악구 신림로 94", "위도": 37.47097701, "경도": 126.9390949, "보안등여부": "Y", "보행신호등여부": "Y", "공공와이파이설치여부": "N", "CCTV설치여부": "Y", "LED비상벨설치여부": "Y", "시각장애인용 음양신호기 여부": "Y", "스피커탑재여부": "Y", "로고젝터 탑재여부": "N", "lat": 37.47097701, "lon": 126.9390949, "facility_group": "smartpole", "center_lon": 126.9390949, "center_lat": 37.47097701, "geometry_wkt": "POINT (126.939095 37.470977)", "source_dataset": "Gwanak Smartpole CSV" }, "geometry": { "type": "Point", "coordinates": [ 126.9390949, 37.47097701 ] } },
{ "type": "Feature", "properties": { "연번": 4, "스마트폴 유형": "어린이보호구역 통합안전 스마트폴", "설치장소": "서울특별시 관악구 신림동 549-8", "위도": 37.48422772, "경도": 126.9103009, "보안등여부": "N", "보행신호등여부": "N", "공공와이파이설치여부": "N", "CCTV설치여부": "Y", "LED비상벨설치여부": "Y", "시각장애인용 음양신호기 여부": "N", "스피커탑재여부": "Y", "로고젝터 탑재여부": "N", "lat": 37.48422772, "lon": 126.9103009, "facility_group": "smartpole", "center_lon": 126.9103009, "center_lat": 37.48422772, "geometry_wkt": "POINT (126.910301 37.484228)", "source_dataset": "Gwanak Smartpole CSV" }, "geometry": { "type": "Point", "coordinates": [ 126.9103009, 37.48422772 ] } },
{ "type": "Feature", "properties": { "연번": 5, "스마트폴 유형": "어린이보호구역 통합안전 스마트폴", "설치장소": "서울특별시 관악구 신림동 602-4", "위도": 37.47606283, "경도": 126.9180317, "보안등여부": "N", "보행신호등여부": "N", "공공와이파이설치여부": "N", "CCTV설치여부": "Y", "LED비상벨설치여부": "Y", "시각장애인용 음양신호기 여부": "N", "스피커탑재여부": "Y", "로고젝터 탑재여부": "N", "lat": 37.47606283, "lon": 126.9180317, "facility_group": "smartpole", "center_lon": 126.9180317, "center_lat": 37.47606283, "geometry_wkt": "POINT (126.918032 37.476063)", "source_dataset": "Gwanak Smartpole CSV" }, "geometry": { "type": "Point", "coordinates": [ 126.9180317, 37.47606283 ] } },
{ "type": "Feature", "properties": { "연번": 6, "스마트폴 유형": "어린이보호구역 통합안전 스마트폴", "설치장소": "서울특별시 관악구 신림동 산202-7", "위도": 37.47745753, "경도": 126.9134624, "보안등여부": "N", "보행신호등여부": "N", "공공와이파이설치여부": "N", "CCTV설치여부": "Y", "LED비상벨설치여부": "Y", "시각장애인용 음양신호기 여부": "N", "스피커탑재여부": "Y", "로고젝터 탑재여부": "N", "lat": 37.47745753, "lon": 126.9134624, "facility_group": "smartpole", "center_lon": 126.9134624, "center_lat": 37.47745753, "geometry_wkt": "POINT (126.913462 37.477458)", "source_dataset": "Gwanak Smartpole CSV" }, "geometry": { "type": "Point", "coordinates": [ 126.9134624, 37.47745753 ] } },
{ "type": "Feature", "properties": { "연번": 7, "스마트폴 유형": "어린이보호구역 통합안전 스마트폴", "설치장소": "서울특별시 관악구 봉천동 300-19", "위도": 37.47585016, "경도": 126.9592816, "보안등여부": "N", "보행신호등여부": "N", "공공와이파이설치여부": "N", "CCTV설치여부": "Y", "LED비상벨설치여부": "Y", "시각장애인용 음양신호기 여부": "N", "스피커탑재여부": "Y", "로고젝터 탑재여부": "N", "lat": 37.47585016, "lon": 126.9592816, "facility_group": "smartpole", "center_lon": 126.9592816, "center_lat": 37.47585016, "geometry_wkt": "POINT (126.959282 37.47585)", "source_dataset": "Gwanak Smartpole CSV" }, "geometry": { "type": "Point", "coordinates": [ 126.9592816, 37.47585016 ] } }
]
}
